CHANGES
MANIFEST.in
README.md
README.rst
requirements.txt
salt-nanny
setup.cfg
setup.py
saltnanny/__init__.py
saltnanny/salt_nanny.py
saltnanny/salt_nanny_client.py
saltnanny/salt_nanny_tool.py
saltnanny/salt_return_parser.py
saltnanny.egg-info/PKG-INFO
saltnanny.egg-info/SOURCES.txt
saltnanny.egg-info/dependency_links.txt
saltnanny.egg-info/requires.txt
saltnanny.egg-info/top_level.txt
tests/requirements.txt