Metadata-Version: 1.0
Name: saltnanny
Version: 0.2.2
Summary: Python Module that parses salt returns stored in an external job cache and logs output
Home-page: https://github.com/dandb/salt-nanny
Author: Dun and Bradstreet Inc.
Author-email: devops@dandb.com
License: GPLv3
Keywords: Salt SaltStack Redis redis_return parse cache external
Platform: UNKNOWN
